Metadata-Version: 2.1
Name: ifb-wrapper-8
Version: 0.0.1
Summary: iFormBuilder API Wrapper
Home-page: https://github.com/jhsu98/ifb-wrapper
Author: Jonathan Hsu
Author-email: jhsu@zerionsoftware.com
License: MIT
Platform: UNKNOWN
Requires-Python: >=3.0
